{
    "openapi": "3.0.0",
    "info": {
        "title": "WishShop API",
        "contact": {
            "email": "lijy91@foxmail.com"
        },
        "version": "1.0.0"
    },
    "servers": [
        {
            "url": "http://localhost:8000",
            "description": "WishShop Server (Local)"
        },
        {
            "url": "http://127.0.0.1:8000",
            "description": "WishShop Server (Local)"
        },
        {
            "url": "https://wishshop-api-dev.thecode.me",
            "description": "WishShop Server (Development)"
        },
        {
            "url": "https://wishshop-api.thecode.me",
            "description": "WishShop Server (Production)"
        }
    ],
    "paths": {
        "/accounts/register": {
            "post": {
                "tags": [
                    "account"
                ],
                "operationId": "App\\Http\\Controllers\\AccountController::register",
                "requestBody": {
                    "required": true,
                    "content": {
                        "application/json": {
                            "schema": {
                                "properties": {
                                    "name": {
                                        "type": "string"
                                    },
                                    "email": {
                                        "type": "string"
                                    },
                                    "password": {
                                        "type": "string"
                                    }
                                },
                                "type": "object"
                            }
                        }
                    }
                },
                "responses": {
                    "200": {
                        "description": ""
                    }
                }
            }
        },
        "/accounts/login": {
            "post": {
                "tags": [
                    "account"
                ],
                "operationId": "App\\Http\\Controllers\\AccountController::login",
                "requestBody": {
                    "required": true,
                    "content": {
                        "application/json": {
                            "schema": {
                                "properties": {
                                    "email": {
                                        "type": "string"
                                    },
                                    "password": {
                                        "type": "string"
                                    }
                                },
                                "type": "object"
                            }
                        }
                    }
                },
                "responses": {
                    "200": {
                        "description": ""
                    }
                }
            }
        },
        "/accounts/logout": {
            "post": {
                "tags": [
                    "account"
                ],
                "operationId": "App\\Http\\Controllers\\AccountController::logout",
                "responses": {
                    "200": {
                        "description": ""
                    }
                },
                "security": [
                    {
                        "jwt_auth": []
                    }
                ]
            }
        },
        "/stores/{store_id}/addresses": {
            "get": {
                "tags": [
                    "addresses"
                ],
                "summary": "Get all Addresses",
                "operationId": "App\\Http\\Controllers\\AddressController::index",
                "parameters": [
                    {
                        "name": "store_id",
                        "in": "path",
                        "description": "Store Id (or slug)",
                        "required": true,
                        "schema": {
                            "type": "string"
                        }
                    },
                    {
                        "name": "page",
                        "in": "query",
                        "description": "Page",
                        "schema": {
                            "type": "integer"
                        }
                    },
                    {
                        "name": "per_page",
                        "in": "query",
                        "description": "Per page",
                        "schema": {
                            "type": "integer"
                        }
                    }
                ],
                "responses": {
                    "200": {
                        "description": ""
                    }
                },
                "security": [
                    {
                        "jwt_auth": []
                    }
                ]
            },
            "post": {
                "tags": [
                    "addresses"
                ],
                "summary": "Create a address",
                "operationId": "App\\Http\\Controllers\\AddressController::store",
                "parameters": [
                    {
                        "name": "store_id",
                        "in": "path",
                        "description": "Store Id (or slug)",
                        "required": true,
                        "schema": {
                            "type": "string"
                        }
                    }
                ],
                "requestBody": {
                    "required": true,
                    "content": {
                        "application/json": {
                            "schema": {
                                "properties": {
                                    "full_name": {
                                        "description": "Full name",
                                        "type": "string"
                                    }
                                },
                                "type": "object"
                            }
                        }
                    }
                },
                "responses": {
                    "200": {
                        "description": ""
                    }
                },
                "security": [
                    {
                        "jwt_auth": []
                    }
                ]
            }
        },
        "/stores/{store_id}/addresses/{address_id}": {
            "get": {
                "tags": [
                    "addresses"
                ],
                "summary": "Get a specific address",
                "operationId": "App\\Http\\Controllers\\AddressController::show",
                "parameters": [
                    {
                        "name": "store_id",
                        "in": "path",
                        "description": "Store Id (or slug)",
                        "required": true,
                        "schema": {
                            "type": "string"
                        }
                    },
                    {
                        "name": "address_id",
                        "in": "path",
                        "description": "Address Id (or slug)",
                        "required": true,
                        "schema": {
                            "type": "string"
                        }
                    }
                ],
                "responses": {
                    "200": {
                        "description": ""
                    }
                },
                "security": [
                    {
                        "jwt_auth": []
                    }
                ]
            },
            "delete": {
                "tags": [
                    "addresses"
                ],
                "summary": "Delete a address",
                "operationId": "App\\Http\\Controllers\\AddressController::destroy",
                "parameters": [
                    {
                        "name": "store_id",
                        "in": "path",
                        "description": "Store Id (or slug)",
                        "required": true,
                        "schema": {
                            "type": "string"
                        }
                    },
                    {
                        "name": "address_id",
                        "in": "path",
                        "description": "Address Id",
                        "required": true,
                        "schema": {
                            "type": "integer"
                        }
                    }
                ],
                "responses": {
                    "200": {
                        "description": ""
                    }
                },
                "security": [
                    {
                        "jwt_auth": []
                    }
                ]
            },
            "patch": {
                "tags": [
                    "addresses"
                ],
                "summary": "Update a address",
                "operationId": "App\\Http\\Controllers\\AddressController::update",
                "parameters": [
                    {
                        "name": "store_id",
                        "in": "path",
                        "description": "Store Id (or slug)",
                        "required": true,
                        "schema": {
                            "type": "string"
                        }
                    },
                    {
                        "name": "address_id",
                        "in": "path",
                        "description": "Address Id",
                        "required": true,
                        "schema": {
                            "type": "integer"
                        }
                    }
                ],
                "requestBody": {
                    "required": true,
                    "content": {
                        "application/json": {
                            "schema": {
                                "properties": {
                                    "full_name": {
                                        "description": "Full name",
                                        "type": "string"
                                    }
                                },
                                "type": "object"
                            }
                        }
                    }
                },
                "responses": {
                    "200": {
                        "description": ""
                    }
                },
                "security": [
                    {
                        "jwt_auth": []
                    }
                ]
            }
        },
        "/stores/{store_id}/brands": {
            "get": {
                "tags": [
                    "brands"
                ],
                "summary": "Get all Brands",
                "operationId": "App\\Http\\Controllers\\BrandController::index",
                "parameters": [
                    {
                        "name": "store_id",
                        "in": "path",
                        "description": "Store Id (or slug)",
                        "required": true,
                        "schema": {
                            "type": "string"
                        }
                    },
                    {
                        "name": "page",
                        "in": "query",
                        "description": "Page",
                        "schema": {
                            "type": "integer"
                        }
                    },
                    {
                        "name": "per_page",
                        "in": "query",
                        "description": "Per page",
                        "schema": {
                            "type": "integer"
                        }
                    }
                ],
                "responses": {
                    "200": {
                        "description": ""
                    }
                }
            }
        },
        "/stores/{store_id}/brands/{brand_id}": {
            "get": {
                "tags": [
                    "brands"
                ],
                "summary": "Get a specific brand",
                "operationId": "App\\Http\\Controllers\\BrandController::show",
                "parameters": [
                    {
                        "name": "store_id",
                        "in": "path",
                        "description": "Store Id (or slug)",
                        "required": true,
                        "schema": {
                            "type": "string"
                        }
                    },
                    {
                        "name": "brand_id",
                        "in": "path",
                        "description": "Brand Id (or slug)",
                        "required": true,
                        "schema": {
                            "type": "string"
                        }
                    }
                ],
                "responses": {
                    "200": {
                        "description": ""
                    }
                }
            }
        },
        "/stores/{store_id}/categories": {
            "get": {
                "tags": [
                    "categories"
                ],
                "summary": "Get all Categories",
                "operationId": "App\\Http\\Controllers\\CategoryController::index",
                "parameters": [
                    {
                        "name": "store_id",
                        "in": "path",
                        "description": "Store Id (or slug)",
                        "required": true,
                        "schema": {
                            "type": "string"
                        }
                    },
                    {
                        "name": "page",
                        "in": "query",
                        "description": "Page",
                        "schema": {
                            "type": "integer"
                        }
                    },
                    {
                        "name": "per_page",
                        "in": "query",
                        "description": "Per page",
                        "schema": {
                            "type": "integer"
                        }
                    },
                    {
                        "name": "parent_id",
                        "in": "query",
                        "description": "Parent Id (or slug)",
                        "schema": {
                            "type": "string"
                        }
                    }
                ],
                "responses": {
                    "200": {
                        "description": ""
                    }
                }
            }
        },
        "/stores/{store_id}/categories/{category_id}": {
            "get": {
                "tags": [
                    "categories"
                ],
                "summary": "Get a specific category",
                "operationId": "App\\Http\\Controllers\\CategoryController::show",
                "parameters": [
                    {
                        "name": "store_id",
                        "in": "path",
                        "description": "Store Id (or slug)",
                        "required": true,
                        "schema": {
                            "type": "string"
                        }
                    },
                    {
                        "name": "category_id",
                        "in": "path",
                        "description": "Category Id (or slug)",
                        "required": true,
                        "schema": {
                            "type": "string"
                        }
                    }
                ],
                "responses": {
                    "200": {
                        "description": ""
                    }
                }
            }
        },
        "/stores/{store_id}/collections": {
            "get": {
                "tags": [
                    "collections"
                ],
                "summary": "Get all Collections",
                "operationId": "App\\Http\\Controllers\\CollectionController::index",
                "parameters": [
                    {
                        "name": "store_id",
                        "in": "path",
                        "description": "Store Id (or slug)",
                        "required": true,
                        "schema": {
                            "type": "string"
                        }
                    },
                    {
                        "name": "page",
                        "in": "query",
                        "description": "Page",
                        "schema": {
                            "type": "integer"
                        }
                    },
                    {
                        "name": "per_page",
                        "in": "query",
                        "description": "Per page",
                        "schema": {
                            "type": "integer"
                        }
                    }
                ],
                "responses": {
                    "200": {
                        "description": ""
                    }
                }
            }
        },
        "/stores/{store_id}/collections/{collection_id}": {
            "get": {
                "tags": [
                    "collections"
                ],
                "summary": "Get a specific collection",
                "operationId": "App\\Http\\Controllers\\CollectionController::show",
                "parameters": [
                    {
                        "name": "store_id",
                        "in": "path",
                        "description": "Store Id",
                        "required": true,
                        "schema": {
                            "type": "string"
                        }
                    },
                    {
                        "name": "collection_id",
                        "in": "path",
                        "description": "Collection Id (or slug)",
                        "required": true,
                        "schema": {
                            "type": "string"
                        }
                    }
                ],
                "responses": {
                    "200": {
                        "description": ""
                    }
                }
            }
        },
        "/stores/{store_id}/favorites": {
            "get": {
                "tags": [
                    "favorites"
                ],
                "summary": "Get all Favorites",
                "operationId": "App\\Http\\Controllers\\FavoriteController::index",
                "parameters": [
                    {
                        "name": "store_id",
                        "in": "path",
                        "description": "Store Id (or slug)",
                        "required": true,
                        "schema": {
                            "type": "string"
                        }
                    },
                    {
                        "name": "page",
                        "in": "query",
                        "description": "Page",
                        "schema": {
                            "type": "integer"
                        }
                    },
                    {
                        "name": "per_page",
                        "in": "query",
                        "description": "Per page",
                        "schema": {
                            "type": "integer"
                        }
                    },
                    {
                        "name": "include",
                        "in": "query",
                        "description": "Include",
                        "schema": {
                            "type": "array",
                            "items": {
                                "type": "string"
                            }
                        }
                    }
                ],
                "responses": {
                    "200": {
                        "description": ""
                    }
                },
                "security": [
                    {
                        "jwt_auth": []
                    }
                ]
            },
            "post": {
                "tags": [
                    "favorites"
                ],
                "summary": "Create a favorite",
                "operationId": "App\\Http\\Controllers\\FavoriteController::store",
                "parameters": [
                    {
                        "name": "store_id",
                        "in": "path",
                        "description": "Store Id (or slug)",
                        "required": true,
                        "schema": {
                            "type": "string"
                        }
                    }
                ],
                "requestBody": {
                    "required": true,
                    "content": {
                        "application/json": {
                            "schema": {
                                "properties": {
                                    "target_type": {
                                        "description": "Target type",
                                        "type": "string"
                                    },
                                    "target_id": {
                                        "description": "Target Id",
                                        "type": "string"
                                    }
                                },
                                "type": "object"
                            }
                        }
                    }
                },
                "responses": {
                    "200": {
                        "description": ""
                    }
                },
                "security": [
                    {
                        "jwt_auth": []
                    }
                ]
            }
        },
        "/stores/{store_id}/favorites/{favorite_id}": {
            "delete": {
                "tags": [
                    "favorites"
                ],
                "summary": "Delete a favorite",
                "operationId": "App\\Http\\Controllers\\FavoriteController::destroy",
                "parameters": [
                    {
                        "name": "store_id",
                        "in": "path",
                        "description": "Store Id (or slug)",
                        "required": true,
                        "schema": {
                            "type": "string"
                        }
                    },
                    {
                        "name": "favorite_id",
                        "in": "path",
                        "description": "Favorite Id",
                        "required": true,
                        "schema": {
                            "type": "integer"
                        }
                    }
                ],
                "responses": {
                    "200": {
                        "description": ""
                    }
                },
                "security": [
                    {
                        "jwt_auth": []
                    }
                ]
            }
        },
        "/stores/{store_id}/orders": {
            "get": {
                "tags": [
                    "orders"
                ],
                "summary": "Get all Orders",
                "operationId": "App\\Http\\Controllers\\OrderController::index",
                "parameters": [
                    {
                        "name": "store_id",
                        "in": "path",
                        "description": "Store Id (or slug)",
                        "required": true,
                        "schema": {
                            "type": "string"
                        }
                    },
                    {
                        "name": "page",
                        "in": "query",
                        "description": "Page",
                        "schema": {
                            "type": "integer"
                        }
                    },
                    {
                        "name": "per_page",
                        "in": "query",
                        "description": "Per page",
                        "schema": {
                            "type": "integer"
                        }
                    }
                ],
                "responses": {
                    "200": {
                        "description": ""
                    }
                },
                "security": [
                    {
                        "jwt_auth": []
                    }
                ]
            }
        },
        "/stores/{store_id}/orders/{number}": {
            "get": {
                "tags": [
                    "orders"
                ],
                "summary": "Get a specific order",
                "operationId": "App\\Http\\Controllers\\OrderController::show",
                "parameters": [
                    {
                        "name": "store_id",
                        "in": "path",
                        "description": "Store Id (or slug)",
                        "required": true,
                        "schema": {
                            "type": "string"
                        }
                    },
                    {
                        "name": "number",
                        "in": "path",
                        "description": "Order number",
                        "required": true,
                        "schema": {
                            "type": "string"
                        }
                    }
                ],
                "responses": {
                    "200": {
                        "description": ""
                    }
                },
                "security": [
                    {
                        "jwt_auth": []
                    }
                ]
            }
        },
        "/stores/{store_id}/orders/{number}/items": {
            "get": {
                "tags": [
                    "orders"
                ],
                "summary": "Get all Items",
                "operationId": "App\\Http\\Controllers\\OrderLineItemController::index",
                "parameters": [
                    {
                        "name": "store_id",
                        "in": "path",
                        "description": "Store Id (or slug)",
                        "required": true,
                        "schema": {
                            "type": "string"
                        }
                    },
                    {
                        "name": "number",
                        "in": "path",
                        "description": "Order number",
                        "required": true,
                        "schema": {
                            "type": "string"
                        }
                    },
                    {
                        "name": "page",
                        "in": "query",
                        "description": "Page",
                        "schema": {
                            "type": "integer"
                        }
                    },
                    {
                        "name": "per_page",
                        "in": "query",
                        "description": "Per page",
                        "schema": {
                            "type": "integer"
                        }
                    }
                ],
                "responses": {
                    "200": {
                        "description": ""
                    }
                },
                "security": [
                    {
                        "jwt_auth": []
                    }
                ]
            }
        },
        "/stores/{store_id}/products": {
            "get": {
                "tags": [
                    "products"
                ],
                "summary": "Get all Products",
                "operationId": "App\\Http\\Controllers\\ProductController::index",
                "parameters": [
                    {
                        "name": "store_id",
                        "in": "path",
                        "description": "Store Id (or slug)",
                        "required": true,
                        "schema": {
                            "type": "string"
                        }
                    },
                    {
                        "name": "page",
                        "in": "query",
                        "description": "Page",
                        "schema": {
                            "type": "integer"
                        }
                    },
                    {
                        "name": "per_page",
                        "in": "query",
                        "description": "Per page",
                        "schema": {
                            "type": "integer"
                        }
                    },
                    {
                        "name": "category_id",
                        "in": "query",
                        "description": "Category Id",
                        "schema": {
                            "type": "integer"
                        }
                    }
                ],
                "responses": {
                    "200": {
                        "description": ""
                    }
                },
                "security": [
                    {
                        "jwt_auth": []
                    }
                ]
            }
        },
        "/stores/{store_id}/products/{product_id}": {
            "get": {
                "tags": [
                    "products"
                ],
                "summary": "Get a specific product",
                "operationId": "App\\Http\\Controllers\\ProductController::show",
                "parameters": [
                    {
                        "name": "store_id",
                        "in": "path",
                        "description": "Store Id (or slug)",
                        "required": true,
                        "schema": {
                            "type": "string"
                        }
                    },
                    {
                        "name": "product_id",
                        "in": "path",
                        "description": "Product Id (or slug)",
                        "required": true,
                        "schema": {
                            "type": "string"
                        }
                    }
                ],
                "responses": {
                    "200": {
                        "description": ""
                    }
                },
                "security": [
                    {
                        "jwt_auth": []
                    }
                ]
            }
        },
        "/stores": {
            "get": {
                "tags": [
                    "stores"
                ],
                "summary": "Get all Stores",
                "operationId": "App\\Http\\Controllers\\StoreController::index",
                "parameters": [
                    {
                        "name": "page",
                        "in": "query",
                        "description": "Page",
                        "schema": {
                            "type": "integer"
                        }
                    },
                    {
                        "name": "per_page",
                        "in": "query",
                        "description": "Per page",
                        "schema": {
                            "type": "integer"
                        }
                    }
                ],
                "responses": {
                    "200": {
                        "description": ""
                    }
                }
            }
        },
        "/stores/{store_id}": {
            "get": {
                "tags": [
                    "stores"
                ],
                "summary": "Get a specific store",
                "operationId": "App\\Http\\Controllers\\StoreController::show",
                "parameters": [
                    {
                        "name": "store_id",
                        "in": "path",
                        "description": "Store Id",
                        "required": true,
                        "schema": {
                            "type": "string"
                        }
                    }
                ],
                "responses": {
                    "200": {
                        "description": ""
                    }
                }
            }
        },
        "/users/{user_id}": {
            "get": {
                "tags": [
                    "users"
                ],
                "summary": "Get a specific user",
                "operationId": "App\\Http\\Controllers\\UserController::show",
                "parameters": [
                    {
                        "name": "user_id",
                        "in": "path",
                        "description": "User Id",
                        "required": true,
                        "schema": {
                            "type": "integer"
                        }
                    }
                ],
                "responses": {
                    "200": {
                        "description": ""
                    }
                }
            }
        }
    },
    "components": {
        "schemas": {
            "Address": {
                "properties": {
                    "id": {
                        "schema": "Address",
                        "type": "integer",
                        "format": "int64"
                    },
                    "store_id": {
                        "schema": "Address",
                        "type": "integer",
                        "format": "int64"
                    },
                    "user_id": {
                        "schema": "Address",
                        "type": "integer",
                        "format": "int64"
                    },
                    "position": {
                        "schema": "Address",
                        "type": "integer",
                        "format": "int64"
                    },
                    "full_name": {
                        "schema": "Address",
                        "type": "string"
                    },
                    "first_name": {
                        "schema": "Address",
                        "type": "string"
                    },
                    "last_name": {
                        "schema": "Address",
                        "type": "string"
                    },
                    "email": {
                        "schema": "Address",
                        "type": "string"
                    },
                    "phone_number": {
                        "schema": "Address",
                        "type": "string"
                    },
                    "country": {
                        "schema": "Address",
                        "type": "string"
                    },
                    "province": {
                        "schema": "Address",
                        "type": "string"
                    },
                    "city": {
                        "schema": "Address",
                        "type": "string"
                    },
                    "district": {
                        "schema": "Address",
                        "type": "string"
                    },
                    "line1": {
                        "schema": "Address",
                        "type": "string"
                    },
                    "line2": {
                        "schema": "Address",
                        "type": "string"
                    },
                    "postal_code": {
                        "schema": "Address",
                        "type": "string"
                    },
                    "deleted_at": {
                        "schema": "Address",
                        "type": "string",
                        "format": "date-time"
                    },
                    "created_at": {
                        "schema": "Address",
                        "type": "string",
                        "format": "date-time"
                    },
                    "updated_at": {
                        "schema": "Address",
                        "type": "string",
                        "format": "date-time"
                    }
                },
                "type": "object"
            },
            "Brand": {
                "properties": {
                    "id": {
                        "schema": "Brand",
                        "type": "integer",
                        "format": "int64"
                    },
                    "user_id": {
                        "schema": "Brand",
                        "type": "integer",
                        "format": "int64"
                    },
                    "slug": {
                        "schema": "Brand",
                        "type": "string"
                    },
                    "position": {
                        "schema": "Brand",
                        "type": "integer",
                        "format": "int64"
                    },
                    "name": {
                        "schema": "Brand",
                        "type": "string"
                    },
                    "image_url": {
                        "schema": "Brand",
                        "type": "string"
                    },
                    "description": {
                        "schema": "Brand",
                        "type": "string"
                    },
                    "deleted_at": {
                        "schema": "Brand",
                        "type": "string",
                        "format": "date-time"
                    },
                    "created_at": {
                        "schema": "Brand",
                        "type": "string",
                        "format": "date-time"
                    },
                    "updated_at": {
                        "schema": "Brand",
                        "type": "string",
                        "format": "date-time"
                    }
                },
                "type": "object"
            },
            "Category": {
                "properties": {
                    "id": {
                        "schema": "Category",
                        "type": "integer",
                        "format": "int64"
                    },
                    "parent_id": {
                        "schema": "Category",
                        "type": "integer",
                        "format": "int64"
                    },
                    "slug": {
                        "schema": "Category",
                        "type": "string"
                    },
                    "position": {
                        "schema": "Category",
                        "type": "integer",
                        "format": "int64"
                    },
                    "name": {
                        "schema": "Category",
                        "type": "string"
                    },
                    "image_url": {
                        "schema": "Category",
                        "type": "string"
                    },
                    "description": {
                        "schema": "Category",
                        "type": "string"
                    },
                    "deleted_at": {
                        "schema": "Category",
                        "type": "string",
                        "format": "date-time"
                    },
                    "created_at": {
                        "schema": "Category",
                        "type": "string",
                        "format": "date-time"
                    },
                    "updated_at": {
                        "schema": "Category",
                        "type": "string",
                        "format": "date-time"
                    }
                },
                "type": "object"
            },
            "Collection": {
                "properties": {
                    "id": {
                        "schema": "Collection",
                        "type": "integer",
                        "format": "int64"
                    },
                    "store_id": {
                        "schema": "Collection",
                        "type": "integer",
                        "format": "int64"
                    },
                    "slug": {
                        "schema": "Collection",
                        "type": "string"
                    },
                    "position": {
                        "schema": "Collection",
                        "type": "integer",
                        "format": "int64"
                    },
                    "name": {
                        "schema": "Collection",
                        "type": "string"
                    },
                    "image_url": {
                        "schema": "Collection",
                        "type": "string"
                    },
                    "description": {
                        "schema": "Collection",
                        "type": "string"
                    },
                    "view_by": {
                        "schema": "Collection",
                        "type": "string"
                    },
                    "status": {
                        "schema": "Collection",
                        "type": "string"
                    },
                    "deleted_at": {
                        "schema": "Collection",
                        "type": "string",
                        "format": "date-time"
                    },
                    "created_at": {
                        "schema": "Collection",
                        "type": "string",
                        "format": "date-time"
                    },
                    "updated_at": {
                        "schema": "Collection",
                        "type": "string",
                        "format": "date-time"
                    }
                },
                "type": "object"
            },
            "CollectionItem": {
                "properties": {
                    "id": {
                        "schema": "CollectionItem",
                        "type": "integer",
                        "format": "int64"
                    },
                    "store_id": {
                        "schema": "CollectionItem",
                        "type": "integer",
                        "format": "int64"
                    },
                    "collection_id": {
                        "schema": "CollectionItem",
                        "type": "integer",
                        "format": "int64"
                    },
                    "position": {
                        "schema": "CollectionItem",
                        "type": "integer",
                        "format": "int64"
                    },
                    "target_type": {
                        "schema": "CollectionItem",
                        "type": "string"
                    },
                    "target_id": {
                        "schema": "CollectionItem",
                        "type": "string"
                    },
                    "deleted_at": {
                        "schema": "CollectionItem",
                        "type": "string",
                        "format": "date-time"
                    },
                    "created_at": {
                        "schema": "CollectionItem",
                        "type": "string",
                        "format": "date-time"
                    },
                    "updated_at": {
                        "schema": "CollectionItem",
                        "type": "string",
                        "format": "date-time"
                    }
                },
                "type": "object"
            },
            "Content": {
                "properties": {
                    "id": {
                        "schema": "Content",
                        "type": "integer",
                        "format": "int64"
                    },
                    "store_id": {
                        "schema": "Content",
                        "type": "integer",
                        "format": "int64"
                    },
                    "target_type": {
                        "schema": "Content",
                        "type": "string"
                    },
                    "target_id": {
                        "schema": "Content",
                        "type": "string"
                    },
                    "position": {
                        "schema": "Content",
                        "type": "integer",
                        "format": "int64"
                    },
                    "type": {
                        "schema": "Content",
                        "type": "string"
                    },
                    "content": {
                        "schema": "Content",
                        "type": "string"
                    },
                    "deleted_at": {
                        "schema": "Content",
                        "type": "string",
                        "format": "date-time"
                    },
                    "created_at": {
                        "schema": "Content",
                        "type": "string",
                        "format": "date-time"
                    },
                    "updated_at": {
                        "schema": "Content",
                        "type": "string",
                        "format": "date-time"
                    }
                },
                "type": "object"
            },
            "Favorite": {
                "properties": {
                    "id": {
                        "schema": "Favorite",
                        "type": "integer",
                        "format": "int64"
                    },
                    "store_id": {
                        "schema": "Favorite",
                        "type": "integer",
                        "format": "int64"
                    },
                    "user_id": {
                        "schema": "Favorite",
                        "type": "integer",
                        "format": "int64"
                    },
                    "target_type": {
                        "schema": "Favorite",
                        "type": "string"
                    },
                    "target_id": {
                        "schema": "Favorite",
                        "type": "string"
                    },
                    "position": {
                        "schema": "Favorite",
                        "type": "integer",
                        "format": "int64"
                    },
                    "deleted_at": {
                        "schema": "Favorite",
                        "type": "string",
                        "format": "date-time"
                    },
                    "created_at": {
                        "schema": "Favorite",
                        "type": "string",
                        "format": "date-time"
                    },
                    "updated_at": {
                        "schema": "Favorite",
                        "type": "string",
                        "format": "date-time"
                    }
                },
                "type": "object"
            },
            "Modifier": {
                "properties": {
                    "id": {
                        "schema": "Modifier",
                        "type": "integer",
                        "format": "int64"
                    },
                    "user_id": {
                        "schema": "Modifier",
                        "type": "integer",
                        "format": "int64"
                    },
                    "product_id": {
                        "schema": "Modifier",
                        "type": "integer",
                        "format": "int64"
                    },
                    "title": {
                        "schema": "Modifier",
                        "type": "string"
                    },
                    "choose_type": {
                        "schema": "Modifier",
                        "type": "string"
                    },
                    "choose_at_least": {
                        "schema": "Modifier",
                        "type": "integer",
                        "format": "int64"
                    },
                    "choose_up_to": {
                        "schema": "Modifier",
                        "type": "integer",
                        "format": "int64"
                    },
                    "deleted_at": {
                        "schema": "Modifier",
                        "type": "string",
                        "format": "date-time"
                    },
                    "created_at": {
                        "schema": "Modifier",
                        "type": "string",
                        "format": "date-time"
                    },
                    "updated_at": {
                        "schema": "Modifier",
                        "type": "string",
                        "format": "date-time"
                    }
                },
                "type": "object"
            },
            "ModifierOption": {
                "properties": {
                    "id": {
                        "schema": "ModifierOption",
                        "type": "integer",
                        "format": "int64"
                    },
                    "user_id": {
                        "schema": "ModifierOption",
                        "type": "integer",
                        "format": "int64"
                    },
                    "slug": {
                        "schema": "ModifierOption",
                        "type": "string"
                    },
                    "name": {
                        "schema": "ModifierOption",
                        "type": "string"
                    },
                    "image_url": {
                        "schema": "ModifierOption",
                        "type": "string"
                    },
                    "description": {
                        "schema": "ModifierOption",
                        "type": "string"
                    },
                    "deleted_at": {
                        "schema": "ModifierOption",
                        "type": "string",
                        "format": "date-time"
                    },
                    "created_at": {
                        "schema": "ModifierOption",
                        "type": "string",
                        "format": "date-time"
                    },
                    "updated_at": {
                        "schema": "ModifierOption",
                        "type": "string",
                        "format": "date-time"
                    }
                },
                "type": "object"
            },
            "Order": {
                "properties": {
                    "id": {
                        "schema": "Order",
                        "type": "integer",
                        "format": "int64"
                    },
                    "store_id": {
                        "schema": "Order",
                        "type": "integer",
                        "format": "int64"
                    },
                    "user_id": {
                        "schema": "Order",
                        "type": "integer",
                        "format": "int64"
                    },
                    "number": {
                        "schema": "Order",
                        "type": "string"
                    },
                    "reference_number": {
                        "schema": "Order",
                        "type": "string"
                    },
                    "subtotal": {
                        "schema": "Order",
                        "type": "number"
                    },
                    "total": {
                        "schema": "Order",
                        "type": "number"
                    },
                    "status": {
                        "schema": "Order",
                        "type": "string"
                    },
                    "deleted_at": {
                        "schema": "Order",
                        "type": "string",
                        "format": "date-time"
                    },
                    "created_at": {
                        "schema": "Order",
                        "type": "string",
                        "format": "date-time"
                    },
                    "updated_at": {
                        "schema": "Order",
                        "type": "string",
                        "format": "date-time"
                    }
                },
                "type": "object"
            },
            "OrderLineItem": {
                "properties": {
                    "id": {
                        "schema": "OrderLineItem",
                        "type": "integer",
                        "format": "int64"
                    },
                    "store_id": {
                        "schema": "OrderLineItem",
                        "type": "integer",
                        "format": "int64"
                    },
                    "user_id": {
                        "schema": "OrderLineItem",
                        "type": "integer",
                        "format": "int64"
                    },
                    "purchase_type": {
                        "schema": "OrderLineItem",
                        "type": "string"
                    },
                    "purchase_id": {
                        "schema": "OrderLineItem",
                        "type": "string"
                    },
                    "label": {
                        "schema": "OrderLineItem",
                        "type": "string"
                    },
                    "price": {
                        "schema": "OrderLineItem",
                        "type": "number"
                    },
                    "original_price": {
                        "schema": "OrderLineItem",
                        "type": "number"
                    },
                    "quantity": {
                        "schema": "OrderLineItem",
                        "type": "number"
                    },
                    "subtotal": {
                        "schema": "OrderLineItem",
                        "type": "number"
                    },
                    "total": {
                        "schema": "OrderLineItem",
                        "type": "number"
                    },
                    "deleted_at": {
                        "schema": "OrderLineItem",
                        "type": "string",
                        "format": "date-time"
                    },
                    "created_at": {
                        "schema": "OrderLineItem",
                        "type": "string",
                        "format": "date-time"
                    },
                    "updated_at": {
                        "schema": "OrderLineItem",
                        "type": "string",
                        "format": "date-time"
                    }
                },
                "type": "object"
            },
            "Product": {
                "properties": {
                    "id": {
                        "schema": "Product",
                        "type": "integer",
                        "format": "int64"
                    },
                    "user_id": {
                        "schema": "Product",
                        "type": "integer",
                        "format": "int64"
                    },
                    "brand_id": {
                        "schema": "Product",
                        "type": "integer",
                        "format": "int64"
                    },
                    "brand_name": {
                        "schema": "Product",
                        "type": "string"
                    },
                    "name": {
                        "schema": "Product",
                        "type": "string"
                    },
                    "image_url": {
                        "schema": "Product",
                        "type": "string"
                    },
                    "description": {
                        "schema": "Product",
                        "type": "string"
                    },
                    "deleted_at": {
                        "schema": "Product",
                        "type": "string",
                        "format": "date-time"
                    },
                    "created_at": {
                        "schema": "Product",
                        "type": "string",
                        "format": "date-time"
                    },
                    "updated_at": {
                        "schema": "Product",
                        "type": "string",
                        "format": "date-time"
                    }
                },
                "type": "object"
            },
            "Store": {
                "properties": {
                    "id": {
                        "schema": "Store",
                        "type": "integer",
                        "format": "int64"
                    },
                    "user_id": {
                        "schema": "Store",
                        "type": "integer",
                        "format": "int64"
                    },
                    "slug": {
                        "schema": "Store",
                        "type": "string"
                    },
                    "name": {
                        "schema": "Store",
                        "type": "string"
                    },
                    "image_url": {
                        "schema": "Store",
                        "type": "string"
                    },
                    "description": {
                        "schema": "Store",
                        "type": "string"
                    },
                    "deleted_at": {
                        "schema": "Store",
                        "type": "string",
                        "format": "date-time"
                    },
                    "created_at": {
                        "schema": "Store",
                        "type": "string",
                        "format": "date-time"
                    },
                    "updated_at": {
                        "schema": "Store",
                        "type": "string",
                        "format": "date-time"
                    }
                },
                "type": "object"
            },
            "User": {
                "properties": {
                    "id": {
                        "schema": "User",
                        "type": "integer",
                        "format": "int64"
                    },
                    "email": {
                        "schema": "User",
                        "type": "string"
                    },
                    "username": {
                        "schema": "User",
                        "type": "string"
                    },
                    "password": {
                        "schema": "User",
                        "type": "string",
                        "format": "password"
                    },
                    "name": {
                        "schema": "User",
                        "type": "string"
                    },
                    "use_gravatar": {
                        "schema": "User",
                        "type": "boolean"
                    },
                    "avatar_url": {
                        "schema": "User",
                        "type": "string"
                    },
                    "age": {
                        "schema": "User",
                        "type": "integer"
                    },
                    "gender": {
                        "schema": "User",
                        "type": "string",
                        "enum": [
                            "secrecy",
                            "male",
                            "female"
                        ]
                    },
                    "birthday": {
                        "schema": "User",
                        "type": "string"
                    },
                    "company": {
                        "schema": "User",
                        "type": "string"
                    },
                    "website": {
                        "schema": "User",
                        "type": "string"
                    },
                    "bio": {
                        "schema": "User",
                        "type": "string"
                    },
                    "status": {
                        "schema": "User",
                        "type": "integer"
                    },
                    "site_admin": {
                        "schema": "User",
                        "type": "boolean"
                    },
                    "deleted_at": {
                        "schema": "User",
                        "type": "string",
                        "format": "date-time"
                    },
                    "created_at": {
                        "schema": "User",
                        "type": "string",
                        "format": "date-time"
                    },
                    "updated_at": {
                        "schema": "User",
                        "type": "string",
                        "format": "date-time"
                    }
                },
                "type": "object"
            }
        },
        "securitySchemes": {
            "jwt_auth": {
                "type": "apiKey",
                "description": "To make authenticated requests via http using the built in methods, you will need to set an authorization header as follows:\\n```\\nAuthorization: Bearer {yourtokenhere}\\n```\\n",
                "name": "Authorization",
                "in": "header"
            }
        }
    },
    "tags": [
        {
            "name": "account",
            "description": ""
        },
        {
            "name": "users",
            "description": ""
        },
        {
            "name": "stores",
            "description": ""
        },
        {
            "name": "brands",
            "description": ""
        },
        {
            "name": "categories",
            "description": ""
        },
        {
            "name": "collections",
            "description": ""
        },
        {
            "name": "products",
            "description": ""
        },
        {
            "name": "addresses",
            "description": ""
        },
        {
            "name": "favorites",
            "description": ""
        },
        {
            "name": "orders",
            "description": ""
        }
    ]
}